einvoicing/__init__.py
einvoicing/einvoicing.py
einvoicing-0.1.0.dist-info/WHEEL
einvoicing-0.1.0.dist-info/METADATA
einvoicing-0.1.0.dist-info/RECORD
