Metadata-Version: 2.1
Name: einvoicing
Version: 0.1.0
Summary: 
Author: samratbanerjea
Author-email: office.samrat@gmail.com
Requires-Python: >=3.7,<4.0
Classifier: Programming Language :: Python :: 3
Classifier: Programming Language :: Python :: 3.7
Classifier: Programming Language :: Python :: 3.8
Classifier: Programming Language :: Python :: 3.9
Requires-Dist: pendulum (>=2.1.2,<3.0.0)
